{
  "$schema": "https://schema.tauri.app/config/2",
  "productName": "wovo",
  "version": "0.1.0",
  "identifier": "com.wovo.desktop",
  "build": {
    "beforeDevCommand": "node ./scripts/trunk.mjs serve",
    "devUrl": "http://localhost:1420",
    "beforeBuildCommand": "node ./scripts/trunk.mjs build",
    "frontendDist": "../dist"
  },
  "app": {
    "withGlobalTauri": false,
    "windows": [
      {
        "title": "WoVo",
        "width": 960,
        "height": 900,
        "minWidth": 640,
        "minHeight": 520
      }
    ],
    "security": {
      "csp": "default-src 'self'; connect-src 'self' ipc: http://ipc.localhost; img-src 'self' data:; font-src 'self'; style-src 'self' 'unsafe-inline'; script-src 'self' 'unsafe-inline' 'wasm-unsafe-eval'; object-src 'none'; base-uri 'none'; frame-ancestors 'none'",
      "devCsp": "default-src 'self'; connect-src 'self' ipc: http://ipc.localhost http://localhost:1420 ws://localhost:1420 http://127.0.0.1:1420 ws://127.0.0.1:1420; img-src 'self' data:; font-src 'self'; style-src 'self' 'unsafe-inline'; script-src 'self' 'unsafe-inline' 'wasm-unsafe-eval'; object-src 'none'; base-uri 'none'; frame-ancestors 'none'",
      "freezePrototype": true
    }
  },
  "bundle": {
    "active": true,
    "targets": "all",
    "icon": [
      "icons/32x32.png",
      "icons/128x128.png",
      "icons/128x128@2x.png",
      "icons/icon.icns",
      "icons/icon.ico"
    ],
    "linux": {
      "deb": {
        "desktopTemplate": "desktop-template.desktop"
      },
      "rpm": {
        "desktopTemplate": "desktop-template.desktop"
      }
    }
  },
  "plugins": {
    "updater": {
      "pubkey": "dW50cnVzdGVkIGNvbW1lbnQ6IG1pbmlzaWduIHB1YmxpYyBrZXk6IDZFMDFCMzU5NzBBMDYyNDAKUldSQVlxQndXYk1CYmtxeDRHdzlORWs0U0FCSFhMZ1ByWGoybTNpRGJLNFBtTU5Za2dRVktTWmUK",
      "endpoints": [
        "https://github.com/arvemy/wovo/releases/latest/download/latest.json"
      ],
      "windows": {
        "installMode": "passive"
      }
    }
  }
}
